setup.cfg
setup.py
justlogit/__init__.py
justlogit.egg-info/PKG-INFO
justlogit.egg-info/SOURCES.txt
justlogit.egg-info/dependency_links.txt
justlogit.egg-info/not-zip-safe
justlogit.egg-info/requires.txt
justlogit.egg-info/top_level.txt