Metadata-Version: 2.1
Name: justlogit
Version: 1.0.3
Summary: Simple logger for your python program
Author-email: holinim@duck.com
